{
  "IcoMoonType": "selection",
  "icons": [
    {
      "icon": {
        "paths": [
          "M-13125.818-325.818h17454.545v2373.818h-17454.545v-2373.818z",
          "M535.891 611.386c149.954 0 271.515-121.561 271.515-271.515s-121.561-271.515-271.515-271.515c-149.954 0-271.515 121.561-271.515 271.515s121.561 271.515 271.515 271.515zM139.636 837.818h884.364v139.636h-884.364v-139.636z",
          "M0 1000.931v-197.002c0-51.413 41.678-93.091 93.091-93.091h739.828c51.413 0 93.091 41.678 93.091 93.091v197.002h-926.010zM46.545 954.386h832.919v-150.456c0-25.706-20.839-46.545-46.545-46.545h-739.828c-25.706 0-46.545 20.839-46.545 46.545v150.456z",
          "M442.8 634.658c-162.807 0-294.788-131.981-294.788-294.788s131.981-294.788 294.788-294.788c162.807 0 294.788 131.981 294.788 294.788s-131.981 294.788-294.788 294.788zM442.8 588.113c137.101 0 248.242-111.142 248.242-248.242s-111.142-248.242-248.242-248.242c-137.101 0-248.242 111.142-248.242 248.242s111.142 248.242 248.242 248.242z"
        ],
        "attrs": [
          {
            "fill": "rgb(255, 255, 255)"
          },
          {
            "fill": "rgb(255, 211, 0)"
          },
          {
            "fill": "rgb(69, 79, 91)"
          },
          {
            "fill": "rgb(69, 79, 91)"
          }
        ],
        "isMulticolor": true,
        "isMulticolor2": false,
        "grid": 0,
        "tags": [
          "我的"
        ],
        "colorPermutations": {
          "2552110125525525516979911": [
            {
              "f": 2
            },
            {
              "f": 1
            },
            {
              "f": 0
            },
            {
              "f": 0
            }
          ]
        }
      },
      "attrs": [
        {
          "fill": "rgb(255, 255, 255)"
        },
        {
          "fill": "rgb(255, 211, 0)"
        },
        {
          "fill": "rgb(69, 79, 91)"
        },
        {
          "fill": "rgb(69, 79, 91)"
        }
      ],
      "properties": {
        "order": 5,
        "id": 1,
        "name": "我的",
        "prevSize": 32
      },
      "setIdx": 0,
      "setId": 2,
      "iconIdx": 0
    },
    {
      "icon": {
        "paths": [
          "M-3161.043-311.652h16695.652v2270.609h-16695.652v-2270.609z",
          "M249.322 53.426h779.61v915.876h-779.61c-49.177 0-89.043-39.866-89.043-89.043v-737.789c0-49.177 39.866-89.043 89.043-89.043z",
          "M899.819 75.687h-757.349c-36.883 0-66.783 29.9-66.783 66.783v737.789c0 36.883 29.9 66.783 66.783 66.783h757.349v-871.354zM142.47 31.165h801.871v960.398h-801.871c-61.472 0-111.304-49.833-111.304-111.304v-737.789c0-61.472 49.833-111.304 111.304-111.304z",
          "M267.828 75.582v313.184c107.435-67.581 116.902-73.319 126.465-73.319 9.493 0 19.43 5.952 128.328 73.589v-313.455h-254.793zM400.609 359.271c0.364-0.178 0.79-0.4 1.323-0.676-0.222 0.115-0.471 0.246-0.746 0.394l-0.577 0.282zM386.767 358.641c0.489 0.25 0.886 0.455 1.226 0.622-0.499-0.243-0.893-0.451-1.226-0.622zM374.924 374.542c-19.375 11.824-47.935 29.608-85.65 53.333-20.123 12.658-46.698 6.607-59.357-13.516-4.319-6.865-6.61-14.811-6.61-22.921v-360.377h343.836l-0.002 360.633c-0 23.773-19.272 43.045-43.045 43.045-8.027-0-15.894-2.244-22.712-6.48-38.368-23.832-67.419-41.696-87.123-53.575-8.351-5.034-14.998-8.978-19.907-11.813-4.812 2.813-11.3 6.71-19.429 11.671z",
          "M890.868 799.361h-750.441c-38.639 0-69.963 31.323-69.963 69.963s31.323 69.963 69.963 69.963h750.441v-139.925zM140.427 754.839h794.962v228.969h-794.962c-63.228 0-114.484-51.256-114.484-114.484s51.256-114.484 114.484-114.484z"
        ],
        "attrs": [
          {
            "fill": "rgb(255, 255, 255)"
          },
          {
            "fill": "rgb(255, 211, 0)"
          },
          {
            "fill": "rgb(69, 79, 91)"
          },
          {
            "fill": "rgb(69, 79, 91)"
          },
          {
            "fill": "rgb(69, 79, 91)"
          }
        ],
        "width": 1069,
        "isMulticolor": true,
        "isMulticolor2": false,
        "grid": 0,
        "tags": [
          "游记"
        ],
        "colorPermutations": {
          "2552110125525525516979911": [
            {
              "f": 2
            },
            {
              "f": 1
            },
            {
              "f": 0
            },
            {
              "f": 0
            },
            {
              "f": 0
            }
          ]
        }
      },
      "attrs": [
        {
          "fill": "rgb(255, 255, 255)"
        },
        {
          "fill": "rgb(255, 211, 0)"
        },
        {
          "fill": "rgb(69, 79, 91)"
        },
        {
          "fill": "rgb(69, 79, 91)"
        },
        {
          "fill": "rgb(69, 79, 91)"
        }
      ],
      "properties": {
        "order": 6,
        "id": 0,
        "name": "游记",
        "prevSize": 32
      },
      "setIdx": 0,
      "setId": 2,
      "iconIdx": 1
    }
  ],
  "height": 1024,
  "preferences": {
    "showGlyphs": true,
    "showQuickUse": true,
    "showQuickUse2": true,
    "showSVGs": true,
    "fontPref": {
      "prefix": "icon-",
      "metadata": {
        "fontFamily": "icomoon"
      },
      "metrics": {
        "emSize": 1024,
        "baseline": 6.25,
        "whitespace": 50
      },
      "embed": false
    },
    "imagePref": {
      "prefix": "icon-",
      "png": true,
      "useClassSelector": true,
      "color": 0,
      "bgColor": 16777215,
      "classSelector": ".icon",
      "autoHost": true,
      "height": 32,
      "columns": 16,
      "margin": 16
    },
    "historySize": 50,
    "showCodes": true,
    "gridSize": 16,
    "quickUsageToken": {
      "UntitledProject": "OWRjNWU0ZDU4NDljZDY3N2E3NGU5ZWYwYTA4NjA4NDcjMSMxNTI2NjUzNTE3IyMj"
    }
  }
}